client/__init__.py
client/client.py
client/client/__init__.py
client/client/add_contact.py
client/client/client_transport.py
client/client/database.py
client/client/del_contact.py
client/client/main_window.py
client/client/main_window_conv.py
client/client/start_dialog.py
client/client/temp_transport.py
client/common/__init__.py
client/common/decorators.py
client/common/descrptrs.py
client/common/errors.py
client/common/message.py
client/common/metaclasses.py
client/common/transport.py
client/common/utils.py
client/common/variables.py
client/logs/__init__.py
client/logs/config_client_log.py
client/logs/config_server_log.py
client/server/__init__.py
client/server/add_user.py
client/server/config_window.py
client/server/core.py
client/server/database.py
client/server/main_window.py
client/server/remove_user.py
client/server/stat_window.py
client/unit_tests/__init__.py
client/unit_tests/test_client.py
client/unit_tests/test_message.py
client/unit_tests/test_server.py
message_client_by_mokrenko-0.1.2.dist-info/METADATA
message_client_by_mokrenko-0.1.2.dist-info/WHEEL
message_client_by_mokrenko-0.1.2.dist-info/top_level.txt
message_client_by_mokrenko-0.1.2.dist-info/RECORD
