Metadata-Version: 2.1
Name: message-client-by-mokrenko
Version: 0.1.2
Summary: Message Client Package
Home-page: UNKNOWN
Author: Vladimir Mokrenko
Author-email: v.v.mokrenko@gmail.com
License: UNKNOWN
Platform: UNKNOWN
Requires-Dist: PyQt5
Requires-Dist: sqlalchemy
Requires-Dist: pycryptodome
Requires-Dist: pycryptodomex
